platzky/__init__.py
platzky/admin/admin.py
platzky/admin/templates/admin.html
platzky/admin/templates/login.html
platzky/admin/templates/module.html
platzky/attachment/__init__.py
platzky/attachment/constants.py
platzky/attachment/core.py
platzky/attachment/mime_validation.py
platzky/blog/__init__.py
platzky/blog/blog.py
platzky/blog/comment_form.py
platzky/config.py
platzky/db/README.md
platzky/db/__init__.py
platzky/db/db.py
platzky/db/db_loader.py
platzky/db/github_json_db.py
platzky/db/google_json_db.py
platzky/db/graph_ql_db.py
platzky/db/json_db.py
platzky/db/json_file_db.py
platzky/db/mongodb_db.py
platzky/debug/__init__.py
platzky/debug/blueprint.py
platzky/debug/fake_login.py
platzky/engine.py
platzky/feature_flags.py
platzky/feature_flags_wrapper.py
platzky/locale/en/LC_MESSAGES/messages.po
platzky/locale/pl/LC_MESSAGES/messages.po
platzky/models.py
platzky/notifier.py
platzky/platzky.py
platzky/plugin/plugin.py
platzky/plugin/plugin_loader.py
platzky/seo/seo.py
platzky/static/blog.css
platzky/static/styles.css
platzky/telemetry.py
platzky/templates/404.html
platzky/templates/base.html
platzky/templates/blog.html
platzky/templates/body_meta.html
platzky/templates/dynamic_css.html
platzky/templates/feed.xml
platzky/templates/head_meta.html
platzky/templates/page.html
platzky/templates/post.html
platzky/templates/robots.txt
platzky/templates/sitemap.xml
platzky/www_handler.py
platzky-1.4.1.dist-info/METADATA
platzky-1.4.1.dist-info/WHEEL
platzky-1.4.1.dist-info/licenses/LICENSE
platzky-1.4.1.dist-info/RECORD
